mapsims/__init__.py
mapsims/alms.py
mapsims/channel_utils.py
mapsims/cmb.py
mapsims/noise.py
mapsims/runner.py
mapsims/utils.py
mapsims/data/README.rst
mapsims/data/__init__.py
mapsims/data/dump_h5_to_csv.ipynb
mapsims/data/example_config_v0.2.toml
mapsims/data/extract_so_instrument_parameters.ipynb
mapsims/data/simonsobs_instrument_parameters_2020.06.csv
mapsims/data/planck_deltabandpass/planck_deltabandpass.tbl
mapsims/data/simonsobs_instrument_parameters_2020.06/bandpass_LF1.tbl
mapsims/data/simonsobs_instrument_parameters_2020.06/bandpass_LF2.tbl
mapsims/data/simonsobs_instrument_parameters_2020.06/bandpass_MFF1.tbl
mapsims/data/simonsobs_instrument_parameters_2020.06/bandpass_MFF2.tbl
mapsims/data/simonsobs_instrument_parameters_2020.06/bandpass_MFS1.tbl
mapsims/data/simonsobs_instrument_parameters_2020.06/bandpass_MFS2.tbl
mapsims/data/simonsobs_instrument_parameters_2020.06/bandpass_UHF1.tbl
mapsims/data/simonsobs_instrument_parameters_2020.06/bandpass_UHF2.tbl
mapsims/data/simonsobs_instrument_parameters_2020.06/simonsobs_instrument_parameters_2020.06.tbl
mapsims/extern/__init__.py
mapsims/tests/__init__.py
mapsims/tests/coveragerc
mapsims/tests/setup_package.py
mapsims/tests/test_alms.py
mapsims/tests/test_cmb.py
mapsims/tests/test_load_hitmaps.ipynb
mapsims/tests/test_noise.py
mapsims/tests/test_noise_SAT.ipynb
mapsims/tests/test_noise_extern.py
mapsims/tests/test_noise_xcorr.ipynb
mapsims/tests/test_parse.py
mapsims/tests/test_parse_channels.py
mapsims/tests/test_runner_car_healpix.py
mapsims/tests/test_runner_custominstrument.py
mapsims/tests/test_runner_v02.py
mapsims/tests/test_s4sim_202211.py
mapsims/tests/data/README.rst
mapsims/tests/data/ame_high.toml
mapsims/tests/data/cmbs4_ame_high_uKCMB_LAT-LFL1_nside16_0000.fits.gz
mapsims/tests/data/cmbs4_instrument_model.tbl
mapsims/tests/data/common.toml
mapsims/tests/data/fullskyUnlensedUnabberatedCMB_alm_set00_00000.fits
mapsims/tests/data/noise_LA_uKCMB_classical_nside16_channel2_seed1234.fits.gz
mapsims-2.6.0.dist-info/entry_points.txt
mapsims-2.6.0.dist-info/LICENSE
mapsims-2.6.0.dist-info/WHEEL
mapsims-2.6.0.dist-info/METADATA
mapsims-2.6.0.dist-info/RECORD
