Metadata-Version: 2.1
Name: mapsims
Version: 2.6.0
Summary: Map based simulations package for Cosmic Microwave Background experiments
Author: Andrea Zonca
Requires-Python: >=3.7
Classifier: License :: OSI Approved :: BSD License
Requires-Dist: toml
Requires-Dist: pyyaml
Requires-Dist: pixell==0.17.3
Requires-Dist: healpy
Requires-Dist: numpy
Requires-Dist: astropy
Requires-Dist: so_noise_models
Requires-Dist: pysm3
Requires-Dist: pytest ; extra == "test"
Requires-Dist: pytest-astropy ; extra == "test"
Requires-Dist: jupyter_client ; extra == "test"
Requires-Dist: nbformat ; extra == "test"
Requires-Dist: ipykernel ; extra == "test"
Requires-Dist: nbval ; extra == "test"
Project-URL: Documentation, https://mapsims.readthedocs.io
Project-URL: Home, https://github.com/galsci/mapsims
Provides-Extra: test
